synology_dsm/__init__.py
synology_dsm/const.py
synology_dsm/exceptions.py
synology_dsm/helpers.py
synology_dsm/py.typed
synology_dsm/synology_dsm.py
synology_dsm/api/__init__.py
synology_dsm/api/core/__init__.py
synology_dsm/api/core/external_usb.py
synology_dsm/api/core/security.py
synology_dsm/api/core/share.py
synology_dsm/api/core/system.py
synology_dsm/api/core/upgrade.py
synology_dsm/api/core/utilization.py
synology_dsm/api/download_station/__init__.py
synology_dsm/api/download_station/task.py
synology_dsm/api/dsm/__init__.py
synology_dsm/api/dsm/information.py
synology_dsm/api/dsm/network.py
synology_dsm/api/photos/__init__.py
synology_dsm/api/photos/model.py
synology_dsm/api/storage/__init__.py
synology_dsm/api/storage/storage.py
synology_dsm/api/surveillance_station/__init__.py
synology_dsm/api/surveillance_station/camera.py
synology_dsm/api/surveillance_station/const.py
synology_dsm/api/video_station/__init__.py
synology_dsm/api/video_station/video.py
py_synology_api-0.1.0.dist-info/LICENSE
py_synology_api-0.1.0.dist-info/METADATA
py_synology_api-0.1.0.dist-info/WHEEL
py_synology_api-0.1.0.dist-info/entry_points.txt
py_synology_api-0.1.0.dist-info/top_level.txt
py_synology_api-0.1.0.dist-info/RECORD
